qaenv/__init__.py
qaenv-0.0.3.dist-info/LICENSE
qaenv-0.0.3.dist-info/METADATA
qaenv-0.0.3.dist-info/WHEEL
qaenv-0.0.3.dist-info/top_level.txt
qaenv-0.0.3.dist-info/zip-safe
qaenv-0.0.3.dist-info/RECORD
